<?xml version="1.0" encoding="UTF-8"?><theHarvester><cmd>-d google.com -b crtsh,dnsdumpster,hackertarget,otx -l 200 -f /home/j/voraguard/scans/google.com_20260424_010600/raw/harvester</cmd><host><ip>184.23.240.46</ip><hostname>184-23-240-46.cache.google.com</hostname></host><host><ip>219.88.189.149</ip><hostname>219-88-189-149.cache.google.com</hostname></host><host><ip>135.180.176.218</ip><hostname>135-180-176-218.cache.google.com</hostname></host><host><ip>142.251.2.100</ip><hostname>activity.google.com</hostname></host><host><ip>189.124.80.82</ip><hostname>82.80.124.189.cache.google.com</hostname></host><host><ip>186.237.52.44</ip><hostname>186-237-52-44.cache.google.com</hostname></host><host><ip>202.128.15.13</ip><hostname>13.cache.google.com</hostname></host><host><ip>189.124.80.87</ip><hostname>87.80.124.189.cache.google.com</hostname></host><host><ip>103.162.254.78</ip><hostname>de-cix.ase.google.com</hostname></host><host><ip>216.155.64.14</ip><hostname>216.155.64.14.cache.google.com</hostname></host><host><ip>219.88.189.197</ip><hostname>219-88-189-197.cache.google.com</hostname></host><host><ip>172.253.124.139</ip><hostname>adscreativestudio.google.com</hostname></host><host><ip>202.128.15.10</ip><hostname>10.cache.google.com</hostname></host><host><ip>219.88.189.167</ip><hostname>219-88-189-167.cache.google.com</hostname></host><host><ip>173.234.14.228</ip><hostname>01sin.google.com</hostname></host><host><ip>92.241.132.95</ip><hostname>95-cache-blicnet.google.com</hostname></host><host><ip>189.39.126.14</ip><hostname>14.126.39.189.cache.google.com</hostname></host><host><ip>186.237.52.12</ip><hostname>186-237-52-12.cache.google.com</hostname></host><host><ip>189.39.126.63</ip><hostname>63.126.39.189.cache.google.com</hostname></host><host><ip>189.124.80.107</ip><hostname>107.80.124.189.cache.google.com</hostname></host><host><ip>177.129.16.107</ip><hostname>177.129.16.107.cache.google.com</hostname></host><host><ip>177.129.16.123</ip><hostname>177.129.16.123.cache.google.com</hostname></host><host><ip>189.124.80.118</ip><hostname>118.80.124.189.cache.google.com</hostname></host><host><ip>103.225.11.118</ip><hostname>103.225.11.118.google.com</hostname></host><host><ip>193.109.188.133</ip><hostname>edgoo-pni.ams.google.com</hostname></host><host><ip>135.180.176.246</ip><hostname>135-180-176-246.cache.google.com</hostname></host><host><ip>186.237.52.14</ip><hostname>186-237-52-14.cache.google.com</hostname></host><host><ip>43.228.124.8</ip><hostname>43.228.124.8.google.com</hostname></host><host><ip>186.237.52.58</ip><hostname>186-237-52-58.cache.google.com</hostname></host><host><ip>189.39.126.53</ip><hostname>53.126.39.189.cache.google.com</hostname></host><host><ip>216.155.64.13</ip><hostname>216.155.64.13.cache.google.com</hostname></host><host><ip>202.128.15.21</ip><hostname>21.cache.google.com</hostname></host><host><ip>177.129.16.102</ip><hostname>177.129.16.102.cache.google.com</hostname></host><host><ip>135.180.176.251</ip><hostname>135-180-176-251.cache.google.com</hostname></host><host><ip>189.124.80.64</ip><hostname>64.80.124.189.cache.google.com</hostname></host><host><ip>92.241.132.113</ip><hostname>113-cache-blicnet.google.com</hostname></host><host><ip>92.241.132.89</ip><hostname>89-cache-blicnet.google.com</hostname></host><host><ip>202.128.15.0</ip><hostname>0.cache.google.com</hostname></host><host><ip>219.88.189.131</ip><hostname>219-88-189-131.cache.google.com</hostname></host><host><ip>92.241.132.92</ip><hostname>92-cache-blicnet.google.com</hostname></host><host><ip>184.23.240.58</ip><hostname>184-23-240-58.cache.google.com</hostname></host><host><ip>185.211.219.49</ip><hostname>ipv4.ama-networx.fra.de.as15169.google.com</hostname></host><host><ip>186.237.52.13</ip><hostname>186-237-52-13.cache.google.com</hostname></host><host><ip>66.42.36.224</ip><hostname>66.42.36.224.google.com</hostname></host><host><ip>219.88.189.179</ip><hostname>219-88-189-179.cache.google.com</hostname></host><host><ip>216.239.45.35</ip><hostname>216-239-45-35.google.com</hostname></host><host><ip>184.23.240.38</ip><hostname>184-23-240-38.cache.google.com</hostname></host><host><ip>24.56.144.126</ip><hostname>126.cache.google.com</hostname></host><host><ip>186.237.52.22</ip><hostname>186-237-52-22.cache.google.com</hostname></host><host><ip>186.237.52.5</ip><hostname>186-237-52-5.cache.google.com</hostname></host><host><ip>177.129.16.108</ip><hostname>177.129.16.108.cache.google.com</hostname></host><host><ip>189.124.80.115</ip><hostname>115.80.124.189.cache.google.com</hostname></host><host><ip>189.39.126.26</ip><hostname>26.126.39.189.cache.google.com</hostname></host><host><ip>186.237.52.32</ip><hostname>186-237-52-32.cache.google.com</hostname></host><host><ip>216.39.250.103</ip><hostname>103-250-39-216.google.com</hostname></host><host><ip>135.180.176.225</ip><hostname>135-180-176-225.cache.google.com</hostname></host><host><ip>219.88.189.187</ip><hostname>219-88-189-187.cache.google.com</hostname></host><host><ip>189.39.126.48</ip><hostname>48.126.39.189.cache.google.com</hostname></host><host><ip>189.124.80.83</ip><hostname>83.80.124.189.cache.google.com</hostname></host><host><ip>135.180.176.210</ip><hostname>135-180-176-210.cache.google.com</hostname></host><host><ip>135.180.176.237</ip><hostname>135-180-176-237.cache.google.com</hostname></host><host><ip>219.88.189.141</ip><hostname>219-88-189-141.cache.google.com</hostname></host><host><ip>219.88.189.153</ip><hostname>219-88-189-153.cache.google.com</hostname></host><host><ip>92.241.132.114</ip><hostname>114-cache-blicnet.google.com</hostname></host><host><ip>189.124.80.92</ip><hostname>92.80.124.189.cache.google.com</hostname></host><host><ip>67.219.201.143</ip><hostname>cache-azo2.google.com</hostname></host><host><ip>135.180.176.202</ip><hostname>135-180-176-202.cache.google.com</hostname></host><host><ip>186.237.52.59</ip><hostname>186-237-52-59.cache.google.com</hostname></host><host><ip>92.241.132.123</ip><hostname>123-cache-blicnet.google.com</hostname></host><host><ip>135.180.176.192</ip><hostname>135-180-176-192.cache.google.com</hostname></host><host><ip>189.39.126.7</ip><hostname>7.126.39.189.cache.google.com</hostname></host><host><ip>208.76.71.226</ip><hostname>4lbbwwcwcywpapprobersecret.google.com</hostname></host><host><ip>202.128.15.17</ip><hostname>17.cache.google.com</hostname></host><host><ip>185.1.8.117</ip><hostname>ipv4.smarthub-2.uae-ix.as15169.google.com</hostname></host><host><ip>184.23.240.45</ip><hostname>184-23-240-45.cache.google.com</hostname></host><host><ip>216.155.64.17</ip><hostname>216.155.64.17.cache.google.com</hostname></host><host><ip>184.23.240.32</ip><hostname>184-23-240-32.cache.google.com</hostname></host><host><ip>216.239.53.82</ip><hostname>216-239-53-82.google.com</hostname></host><host><ip>219.88.189.152</ip><hostname>219-88-189-152.cache.google.com</hostname></host><host><ip>92.241.132.68</ip><hostname>68-cache-blicnet.google.com</hostname></host><host><ip>184.23.240.63</ip><hostname>184-23-240-63.cache.google.com</hostname></host><host><ip>135.180.176.215</ip><hostname>135-180-176-215.cache.google.com</hostname></host><host><ip>219.88.189.157</ip><hostname>219-88-189-157.cache.google.com</hostname></host><host><ip>189.39.126.38</ip><hostname>38.126.39.189.cache.google.com</hostname></host><host><ip>135.180.176.201</ip><hostname>135-180-176-201.cache.google.com</hostname></host><host><ip>135.180.176.209</ip><hostname>135-180-176-209.cache.google.com</hostname></host><host><ip>189.124.80.104</ip><hostname>104.80.124.189.cache.google.com</hostname></host><host><ip>177.129.16.124</ip><hostname>177.129.16.124.cache.google.com</hostname></host><host><ip>186.237.52.2</ip><hostname>186-237-52-2.cache.google.com</hostname></host><host><ip>189.124.80.80</ip><hostname>80.80.124.189.cache.google.com</hostname></host><host><ip>219.88.189.169</ip><hostname>219-88-189-169.cache.google.com</hostname></host><host><ip>189.124.80.88</ip><hostname>88.80.124.189.cache.google.com</hostname></host><host><ip>142.250.68.206</ip><hostname>adsense.google.com</hostname></host><host><ip>189.39.126.21</ip><hostname>21.126.39.189.cache.google.com</hostname></host><host><ip>219.88.189.184</ip><hostname>219-88-189-184.cache.google.com</hostname></host><host><ip>142.250.80.46</ip><hostname>adviser.google.com</hostname></host><host><ip>189.124.80.106</ip><hostname>106.80.124.189.cache.google.com</hostname></host><host><ip>189.39.126.57</ip><hostname>57.126.39.189.cache.google.com</hostname></host><host><ip>184.23.240.48</ip><hostname>184-23-240-48.cache.google.com</hostname></host><host><ip>184.23.240.51</ip><hostname>184-23-240-51.cache.google.com</hostname></host><host><ip>186.237.52.51</ip><hostname>186-237-52-51.cache.google.com</hostname></host><host><ip>189.39.126.36</ip><hostname>36.126.39.189.cache.google.com</hostname></host><host><ip>189.124.80.110</ip><hostname>110.80.124.189.cache.google.com</hostname></host><host><ip>219.88.189.129</ip><hostname>219-88-189-129.cache.google.com</hostname></host><host><ip>186.237.52.50</ip><hostname>186-237-52-50.cache.google.com</hostname></host><host><ip>24.220.1.144</ip><hostname>144.cache.google.com</hostname></host><host><ip>142.251.179.84</ip><hostname>accounts.google.com</hostname></host><host><ip>219.88.189.155</ip><hostname>219-88-189-155.cache.google.com</hostname></host><host><ip>142.251.211.78</ip><hostname>aboutme.google.com</hostname></host><host><ip>216.155.64.19</ip><hostname>216.155.64.19.cache.google.com</hostname></host><host><ip>177.129.16.119</ip><hostname>177.129.16.119.cache.google.com</hostname></host><host><ip>78.46.87.16</ip><hostname>static.16.87.46.78.google.com</hostname></host><host><ip>189.39.126.43</ip><hostname>43.126.39.189.cache.google.com</hostname></host><host><ip>193.188.137.163</ip><hostname>bix.google.com</hostname></host><host><ip>92.241.132.115</ip><hostname>115-cache-blicnet.google.com</hostname></host><host><ip>219.88.189.178</ip><hostname>219-88-189-178.cache.google.com</hostname></host><host><ip>189.39.126.22</ip><hostname>22.126.39.189.cache.google.com</hostname></host><host><ip>216.155.64.20</ip><hostname>216.155.64.20.cache.google.com</hostname></host><host><ip>219.88.189.199</ip><hostname>219-88-189-199.cache.google.com</hostname></host><host><ip>66.42.104.18</ip><hostname>1.1.1.1.google.com</hostname></host><host><ip>189.39.126.1</ip><hostname>1.126.39.189.cache.google.com</hostname></host><host><ip>92.241.132.119</ip><hostname>119-cache-blicnet.google.com</hostname></host><host><ip>92.241.132.71</ip><hostname>71-cache-blicnet.google.com</hostname></host><host><ip>135.180.176.233</ip><hostname>135-180-176-233.cache.google.com</hostname></host><host><ip>219.88.189.150</ip><hostname>219-88-189-150.cache.google.com</hostname></host><host><ip>181.214.99.82</ip><hostname>aaa.google.com</hostname></host><host><ip>177.129.16.101</ip><hostname>177.129.16.101.cache.google.com</hostname></host><host><ip>189.124.80.71</ip><hostname>71.80.124.189.cache.google.com</hostname></host><host><ip>142.251.46.238</ip><hostname>360suite.google.com</hostname></host><host><ip>92.241.132.78</ip><hostname>78-cache-blicnet.google.com</hostname></host><host><ip>189.39.126.51</ip><hostname>51.126.39.189.cache.google.com</hostname></host><host><ip>92.241.132.111</ip><hostname>111-cache-blicnet.google.com</hostname></host><host><ip>219.88.189.161</ip><hostname>219-88-189-161.cache.google.com</hostname></host><host><ip>135.180.176.195</ip><hostname>135-180-176-195.cache.google.com</hostname></host><host><ip>135.180.176.223</ip><hostname>135-180-176-223.cache.google.com</hostname></host><host><ip>92.241.132.112</ip><hostname>112-cache-blicnet.google.com</hostname></host><host><ip>219.88.189.133</ip><hostname>219-88-189-133.cache.google.com</hostname></host><host><ip>200.220.141.228</ip><hostname>nipbr-sjk1.cache-ggc.google.com</hostname></host><host><ip>74.125.137.129</ip><hostname>borgmon.evenflow.adz.google.com</hostname></host><host><ip>92.241.132.77</ip><hostname>77-cache-blicnet.google.com</hostname></host><host><ip>188.191.224.34</ip><hostname>as15169.google.com</hostname></host><host><ip>189.124.80.74</ip><hostname>74.80.124.189.cache.google.com</hostname></host><host><ip>184.23.240.49</ip><hostname>184-23-240-49.cache.google.com</hostname></host><host><ip>186.237.52.38</ip><hostname>186-237-52-38.cache.google.com</hostname></host><host><ip>189.39.126.6</ip><hostname>6.126.39.189.cache.google.com</hostname></host><host><ip>135.180.176.244</ip><hostname>135-180-176-244.cache.google.com</hostname></host><host><ip>186.237.52.6</ip><hostname>186-237-52-6.cache.google.com</hostname></host><host><ip>219.88.189.146</ip><hostname>219-88-189-146.cache.google.com</hostname></host><host><ip>189.124.80.103</ip><hostname>103.80.124.189.cache.google.com</hostname></host><host><ip>142.250.191.78</ip><hostname>adwords-sandbox.google.com</hostname></host><host><ip>219.88.189.140</ip><hostname>219-88-189-140.cache.google.com</hostname></host><host><ip>202.128.15.18</ip><hostname>18.cache.google.com</hostname></host><host><ip>186.237.52.9</ip><hostname>186-237-52-9.cache.google.com</hostname></host><host><ip>219.88.189.202</ip><hostname>219-88-189-202.cache.google.com</hostname></host><host><ip>219.88.189.154</ip><hostname>219-88-189-154.cache.google.com</hostname></host><host><ip>177.129.16.115</ip><hostname>177.129.16.115.cache.google.com</hostname></host><host><ip>135.180.176.217</ip><hostname>135-180-176-217.cache.google.com</hostname></host><host><ip>172.253.115.129</ip><hostname>frame.ads-nightly.qa.adz.google.com</hostname></host><host><ip>189.124.80.99</ip><hostname>99.80.124.189.cache.google.com</hostname></host><host><ip>189.124.80.93</ip><hostname>93.80.124.189.cache.google.com</hostname></host><host><ip>142.251.210.46</ip><hostname>adsdatahub.google.com</hostname></host><host><ip>184.23.240.62</ip><hostname>184-23-240-62.cache.google.com</hostname></host><host><ip>177.129.16.112</ip><hostname>177.129.16.112.cache.google.com</hostname></host><host><ip>189.39.126.19</ip><hostname>19.126.39.189.cache.google.com</hostname></host><host><ip>184.23.240.57</ip><hostname>184-23-240-57.cache.google.com</hostname></host><host><ip>184.23.240.40</ip><hostname>184-23-240-40.cache.google.com</hostname></host><host><ip>189.39.126.5</ip><hostname>5.126.39.189.cache.google.com</hostname></host><host><ip>135.180.176.241</ip><hostname>135-180-176-241.cache.google.com</hostname></host><host><ip>219.88.189.186</ip><hostname>219-88-189-186.cache.google.com</hostname></host><host><ip>186.237.52.54</ip><hostname>186-237-52-54.cache.google.com</hostname></host><host><ip>142.251.45.164</ip><hostname>academico.google.com</hostname></host><host><ip>189.124.80.79</ip><hostname>79.80.124.189.cache.google.com</hostname></host><host><ip>142.251.218.238</ip><hostname>ads.google.com</hostname></host><host><ip>189.39.126.45</ip><hostname>45.126.39.189.cache.google.com</hostname></host><host><ip>184.23.240.60</ip><hostname>184-23-240-60.cache.google.com</hostname></host><host><ip>189.39.126.37</ip><hostname>37.126.39.189.cache.google.com</hostname></host><host><ip>189.39.126.32</ip><hostname>32.126.39.189.cache.google.com</hostname></host><host><ip>216.239.45.4</ip><hostname>216-239-45-4.google.com</hostname></host><host><ip>45.63.110.192</ip><hostname>45.63.110.192.google.com</hostname></host><host><ip>177.36.38.164</ip><hostname>177-36-38-164.cache.google.com</hostname></host><host><ip>189.39.126.12</ip><hostname>12.126.39.189.cache.google.com</hostname></host><host><ip>219.88.189.134</ip><hostname>219-88-189-134.cache.google.com</hostname></host><host><ip>216.155.64.11</ip><hostname>216.155.64.11.cache.google.com</hostname></host><host><ip>177.129.16.122</ip><hostname>177.129.16.122.cache.google.com</hostname></host><host><ip>80.81.192.108</ip><hostname>ipv4.de-cix.fra.de.as15169.google.com</hostname></host><host><ip>142.251.45.174</ip><hostname>ads1.google.com</hostname></host><host><ip>92.241.132.96</ip><hostname>96-cache-blicnet.google.com</hostname></host><host><ip>92.241.132.125</ip><hostname>125-cache-blicnet.google.com</hostname></host><host><ip>142.250.217.142</ip><hostname>adplanner.google.com</hostname></host><host><ip>95.164.50.157</ip><hostname>x0-2007.nline.iev.ua.8772.as.google.com</hostname></host><host><ip>189.39.126.2</ip><hostname>2.126.39.189.cache.google.com</hostname></host><host><ip>184.23.240.59</ip><hostname>184-23-240-59.cache.google.com</hostname></host><host><ip>135.180.176.219</ip><hostname>135-180-176-219.cache.google.com</hostname></host><host><ip>206.53.202.109</ip><hostname>ipv4.de-cix.dfw.us.as15169.google.com</hostname></host><host><ip>186.237.52.36</ip><hostname>186-237-52-36.cache.google.com</hostname></host><host><ip>219.88.189.175</ip><hostname>219-88-189-175.cache.google.com</hostname></host><host><ip>135.180.176.227</ip><hostname>135-180-176-227.cache.google.com</hostname></host><host><ip>202.128.15.12</ip><hostname>12.cache.google.com</hostname></host><host><ip>202.128.15.14</ip><hostname>14.cache.google.com</hostname></host><host><ip>189.124.80.123</ip><hostname>123.80.124.189.cache.google.com</hostname></host><host><ip>219.88.189.174</ip><hostname>219-88-189-174.cache.google.com</hostname></host><host><ip>186.237.52.53</ip><hostname>186-237-52-53.cache.google.com</hostname></host><host><ip>216.155.64.15</ip><hostname>216.155.64.15.cache.google.com</hostname></host><host><ip>186.237.52.4</ip><hostname>186-237-52-4.cache.google.com</hostname></host><host><ip>92.241.132.83</ip><hostname>83-cache-blicnet.google.com</hostname></host><host><ip>189.124.80.127</ip><hostname>127.80.124.189.cache.google.com</hostname></host><host><ip>219.88.189.190</ip><hostname>219-88-189-190.cache.google.com</hostname></host><host><ip>219.88.189.142</ip><hostname>219-88-189-142.cache.google.com</hostname></host><host><ip>24.220.112.166</ip><hostname>166.cache.google.com</hostname></host><host><ip>45.32.10.53</ip><hostname>45.32.10.53.google.com</hostname></host><host><ip>91.183.245.122</ip><hostname>ams.google.com</hostname></host><host><ip>177.129.16.100</ip><hostname>177.129.16.100.cache.google.com</hostname></host><host><ip>186.237.52.41</ip><hostname>186-237-52-41.cache.google.com</hostname></host><host><ip>219.88.189.189</ip><hostname>219-88-189-189.cache.google.com</hostname></host><host><ip>24.56.144.101</ip><hostname>101.cache.google.com</hostname></host><host><ip>189.124.80.96</ip><hostname>96.80.124.189.cache.google.com</hostname></host><host><ip>135.180.176.206</ip><hostname>135-180-176-206.cache.google.com</hostname></host><host><ip>61.32.113.221</ip><hostname>amil.google.com</hostname></host><host><ip>189.124.80.97</ip><hostname>97.80.124.189.cache.google.com</hostname></host><host><ip>142.250.217.14</ip><hostname>aa.google.com</hostname></host><host><ip>191.96.103.149</ip><hostname>191-96-103-149.google.com</hostname></host><host><ip>202.128.15.1</ip><hostname>1.cache.google.com</hostname></host><host><ip>186.237.52.35</ip><hostname>186-237-52-35.cache.google.com</hostname></host><host><ip>89.184.83.137</ip><hostname>botnet.google.com</hostname></host><host><ip>189.39.126.52</ip><hostname>52.126.39.189.cache.google.com</hostname></host><host><ip>219.88.189.196</ip><hostname>219-88-189-196.cache.google.com</hostname></host><host><ip>189.124.80.68</ip><hostname>68.80.124.189.cache.google.com</hostname></host><host><ip>189.124.80.67</ip><hostname>67.80.124.189.cache.google.com</hostname></host><host><ip>135.180.176.222</ip><hostname>135-180-176-222.cache.google.com</hostname></host><host><ip>92.241.132.110</ip><hostname>110-cache-blicnet.google.com</hostname></host><host><ip>142.251.167.129</ip><hostname>frame.ads-devel.qa.adz.google.com</hostname></host><host><ip>189.124.80.105</ip><hostname>105.80.124.189.cache.google.com</hostname></host><host><ip>189.39.126.40</ip><hostname>40.126.39.189.cache.google.com</hostname></host><host><ip>216.155.64.16</ip><hostname>216.155.64.16.cache.google.com</hostname></host><host><ip>64.233.180.101</ip><hostname>adwords.google.com</hostname></host><host><ip>189.124.80.121</ip><hostname>121.80.124.189.cache.google.com</hostname></host><host><ip>92.241.132.121</ip><hostname>121-cache-blicnet.google.com</hostname></host><host><ip>142.250.141.129</ip><hostname>ads-nightly.qa.adz.google.com</hostname></host><host><ip>142.251.210.46</ip><hostname>actionscenter.google.com</hostname></host><host><ip>92.241.132.117</ip><hostname>117-cache-blicnet.google.com</hostname></host><host><ip>186.237.52.10</ip><hostname>186-237-52-10.cache.google.com</hostname></host><host><ip>189.124.80.109</ip><hostname>109.80.124.189.cache.google.com</hostname></host><host><ip>185.1.210.34</ip><hostname>ipv4.de-cix.ham.de.as15169.google.com</hostname></host><host><ip>189.124.80.81</ip><hostname>81.80.124.189.cache.google.com</hostname></host><host><ip>186.237.52.31</ip><hostname>186-237-52-31.cache.google.com</hostname></host><host><ip>216.239.45.33</ip><hostname>216-239-45-33.google.com</hostname></host><host><ip>216.155.64.10</ip><hostname>216.155.64.10.cache.google.com</hostname></host><host><ip>103.225.9.86</ip><hostname>103-225-9-86.google.com</hostname></host><host><ip>24.124.17.164</ip><hostname>164.cache.google.com</hostname></host><host><ip>216.239.45.36</ip><hostname>216-239-45-36.google.com</hostname></host><host><ip>177.129.16.125</ip><hostname>177.129.16.125.cache.google.com</hostname></host><host><ip>186.237.52.34</ip><hostname>186-237-52-34.cache.google.com</hostname></host><host><ip>185.1.47.3</ip><hostname>ipv4.de-cix.mrs.fr.as15169.google.com</hostname></host><host><ip>142.251.219.14</ip><hostname>actualities.google.com</hostname></host><host><ip>92.241.132.108</ip><hostname>108-cache-blicnet.google.com</hostname></host><host><ip>177.129.16.105</ip><hostname>177.129.16.105.cache.google.com</hostname></host><host><ip>142.250.68.206</ip><hostname>adstransparency.google.com</hostname></host><host><ip>186.237.52.18</ip><hostname>186-237-52-18.cache.google.com</hostname></host><host><ip>92.241.132.107</ip><hostname>107-cache-blicnet.google.com</hostname></host><host><ip>189.39.126.46</ip><hostname>46.126.39.189.cache.google.com</hostname></host><host><ip>219.88.189.171</ip><hostname>219-88-189-171.cache.google.com</hostname></host><host><ip>92.241.132.69</ip><hostname>69-cache-blicnet.google.com</hostname></host><host><ip>189.124.80.77</ip><hostname>77.80.124.189.cache.google.com</hostname></host><host><ip>216.155.64.18</ip><hostname>216.155.64.18.cache.google.com</hostname></host><host><ip>95.78.126.52</ip><hostname>95.78.126.52.google.com</hostname></host><host><ip>177.129.16.118</ip><hostname>177.129.16.118.cache.google.com</hostname></host><host><ip>202.128.15.20</ip><hostname>20.cache.google.com</hostname></host><host><ip>189.39.126.31</ip><hostname>31.126.39.189.cache.google.com</hostname></host><host><ip>88.218.93.135</ip><hostname>backupfromnorway.google.com</hostname></host><host><ip>219.88.189.148</ip><hostname>219-88-189-148.cache.google.com</hostname></host><host><ip>189.39.126.41</ip><hostname>41.126.39.189.cache.google.com</hostname></host><host><ip>185.1.131.18</ip><hostname>ipv4.de-cix.lis.pt.as15169.google.com</hostname></host><host><ip>92.241.132.124</ip><hostname>124-cache-blicnet.google.com</hostname></host><host><ip>142.251.16.100</ip><hostname>admob.google.com</hostname></host><host><ip>135.180.176.249</ip><hostname>135-180-176-249.cache.google.com</hostname></host><host><ip>186.237.52.56</ip><hostname>186-237-52-56.cache.google.com</hostname></host><host><ip>185.18.4.38</ip><hostname>br.google.com</hostname></host><host><ip>135.180.176.238</ip><hostname>135-180-176-238.cache.google.com</hostname></host><host><ip>92.241.132.126</ip><hostname>126-cache-blicnet.google.com</hostname></host><host><ip>135.180.176.216</ip><hostname>135-180-176-216.cache.google.com</hostname></host><host><ip>135.180.176.250</ip><hostname>135-180-176-250.cache.google.com</hostname></host><host><ip>64.176.200.190</ip><hostname>64.google.com</hostname></host><host><ip>198.32.132.41</ip><hostname>aix.pr1.atl.google.com</hostname></host><host><ip>92.241.132.66</ip><hostname>66-cache-blicnet.google.com</hostname></host><host><ip>92.241.132.73</ip><hostname>73-cache-blicnet.google.com</hostname></host><host><ip>135.180.176.226</ip><hostname>135-180-176-226.cache.google.com</hostname></host><host><ip>186.237.52.52</ip><hostname>186-237-52-52.cache.google.com</hostname></host><host><ip>135.180.176.240</ip><hostname>135-180-176-240.cache.google.com</hostname></host><host><ip>219.88.189.137</ip><hostname>219-88-189-137.cache.google.com</hostname></host><host><ip>66.102.14.1</ip><hostname>66-102-14-1.google.com</hostname></host><host><ip>92.241.132.109</ip><hostname>109-cache-blicnet.google.com</hostname></host><host><ip>189.124.80.70</ip><hostname>70.80.124.189.cache.google.com</hostname></host><host><ip>189.124.80.111</ip><hostname>111.80.124.189.cache.google.com</hostname></host><host><ip>92.241.132.72</ip><hostname>72-cache-blicnet.google.com</hostname></host><host><ip>217.9.232.129</ip><hostname>cache-gw.google.com</hostname></host><host><ip>135.180.176.231</ip><hostname>135-180-176-231.cache.google.com</hostname></host><host><ip>186.237.52.47</ip><hostname>186-237-52-47.cache.google.com</hostname></host><host><ip>135.180.176.236</ip><hostname>135-180-176-236.cache.google.com</hostname></host><host><ip>202.128.15.16</ip><hostname>16.cache.google.com</hostname></host><host><ip>189.124.80.72</ip><hostname>72.80.124.189.cache.google.com</hostname></host><host><ip>92.241.132.105</ip><hostname>105-cache-blicnet.google.com</hostname></host><host><ip>219.88.189.188</ip><hostname>219-88-189-188.cache.google.com</hostname></host><host><ip>142.251.218.174</ip><hostname>adssettings.google.com</hostname></host><host><ip>123.176.98.119</ip><hostname>119.68.176.123.google.com</hostname></host><host><ip>92.241.132.98</ip><hostname>98-cache-blicnet.google.com</hostname></host><host><ip>135.180.176.245</ip><hostname>135-180-176-245.cache.google.com</hostname></host><host><ip>184.23.240.39</ip><hostname>184-23-240-39.cache.google.com</hostname></host><host><ip>186.237.52.29</ip><hostname>186-237-52-29.cache.google.com</hostname></host><host><ip>184.23.240.56</ip><hostname>184-23-240-56.cache.google.com</hostname></host><host><ip>219.88.189.177</ip><hostname>219-88-189-177.cache.google.com</hostname></host><host><ip>135.180.176.199</ip><hostname>135-180-176-199.cache.google.com</hostname></host><host><ip>219.88.189.160</ip><hostname>219-88-189-160.cache.google.com</hostname></host><host><ip>186.237.52.30</ip><hostname>186-237-52-30.cache.google.com</hostname></host><host><ip>92.241.132.87</ip><hostname>87-cache-blicnet.google.com</hostname></host><host><ip>219.88.189.139</ip><hostname>219-88-189-139.cache.google.com</hostname></host><host><ip>24.56.144.100</ip><hostname>100.cache.google.com</hostname></host><host><ip>43.228.124.179</ip><hostname>43.228.124.179.google.com</hostname></host><host><ip>142.251.2.129</ip><hostname>frame.ads-prod.qa.adz.google.com</hostname></host><host><ip>189.124.80.114</ip><hostname>114.80.124.189.cache.google.com</hostname></host><host><ip>189.39.126.33</ip><hostname>33.126.39.189.cache.google.com</hostname></host><host><ip>189.39.126.23</ip><hostname>23.126.39.189.cache.google.com</hostname></host><host><ip>94.131.123.174</ip><hostname>bot.google.com</hostname></host><host><ip>186.237.52.25</ip><hostname>186-237-52-25.cache.google.com</hostname></host><host><ip>135.180.176.212</ip><hostname>135-180-176-212.cache.google.com</hostname></host><host><ip>189.39.126.44</ip><hostname>44.126.39.189.cache.google.com</hostname></host><host><ip>135.180.176.221</ip><hostname>135-180-176-221.cache.google.com</hostname></host><host><ip>189.124.80.124</ip><hostname>124.80.124.189.cache.google.com</hostname></host><host><ip>135.180.176.197</ip><hostname>135-180-176-197.cache.google.com</hostname></host><host><ip>67.219.192.32</ip><hostname>cache-azo1.google.com</hostname></host><host><ip>189.124.80.113</ip><hostname>113.80.124.189.cache.google.com</hostname></host><host><ip>92.241.132.85</ip><hostname>85-cache-blicnet.google.com</hostname></host><host><ip>103.43.75.111</ip><hostname>103.43.75.111.google.com</hostname></host><host><ip>64.176.220.4</ip><hostname>c7mapi.google.com</hostname></host><host><ip>219.88.189.205</ip><hostname>219-88-189-205.cache.google.com</hostname></host><host><ip>189.124.80.94</ip><hostname>94.80.124.189.cache.google.com</hostname></host><host><ip>65.20.80.24</ip><hostname>65.20.80.24.google.com</hostname></host><host><ip>219.88.189.166</ip><hostname>219-88-189-166.cache.google.com</hostname></host><host><ip>184.23.240.37</ip><hostname>184-23-240-37.cache.google.com</hostname></host><host><ip>135.180.176.198</ip><hostname>135-180-176-198.cache.google.com</hostname></host><host><ip>219.88.189.183</ip><hostname>219-88-189-183.cache.google.com</hostname></host><host><ip>189.39.126.18</ip><hostname>18.126.39.189.cache.google.com</hostname></host><host><ip>219.88.189.193</ip><hostname>219-88-189-193.cache.google.com</hostname></host><host><ip>177.36.38.165</ip><hostname>177-36-38-165.cache.google.com</hostname></host><host><ip>186.237.52.63</ip><hostname>186-237-52-63.cache.google.com</hostname></host><host><ip>189.39.126.49</ip><hostname>49.126.39.189.cache.google.com</hostname></host><host><ip>24.220.112.176</ip><hostname>176.cache.google.com</hostname></host><host><ip>92.241.132.74</ip><hostname>74-cache-blicnet.google.com</hostname></host><host><ip>45.77.95.146</ip><hostname>45.77.95.146.google.com</hostname></host><host><ip>177.129.16.117</ip><hostname>177.129.16.117.cache.google.com</hostname></host><host><ip>189.124.80.69</ip><hostname>69.80.124.189.cache.google.com</hostname></host><host><ip>23.19.231.221</ip><hostname>221.231.19.23.google.com</hostname></host><host><ip>216.239.45.63</ip><hostname>216-239-45-63.google.com</hostname></host><host><ip>184.23.240.61</ip><hostname>184-23-240-61.cache.google.com</hostname></host><host><ip>135.180.176.243</ip><hostname>135-180-176-243.cache.google.com</hostname></host><host><ip>189.39.126.15</ip><hostname>15.126.39.189.cache.google.com</hostname></host><host><ip>24.124.17.190</ip><hostname>190.cache.google.com</hostname></host><host><ip>186.237.52.37</ip><hostname>186-237-52-37.cache.google.com</hostname></host><host><ip>186.237.52.3</ip><hostname>186-237-52-3.cache.google.com</hostname></host><host><ip>189.124.80.101</ip><hostname>101.80.124.189.cache.google.com</hostname></host><host><ip>92.241.132.75</ip><hostname>75-cache-blicnet.google.com</hostname></host><host><ip>186.237.52.43</ip><hostname>186-237-52-43.cache.google.com</hostname></host><host><ip>198.13.54.143</ip><hostname>198.13.54.143.google.com</hostname></host><host><ip>189.124.80.116</ip><hostname>116.80.124.189.cache.google.com</hostname></host><host><ip>189.39.126.54</ip><hostname>54.126.39.189.cache.google.com</hostname></host><host><ip>177.129.16.106</ip><hostname>177.129.16.106.cache.google.com</hostname></host><host><ip>74.125.138.138</ip><hostname>admin.google.com</hostname></host><host><ip>179.109.31.209</ip><hostname>nipbr-sjk2.cache-ggc.google.com</hostname></host><host><ip>219.88.189.185</ip><hostname>219-88-189-185.cache.google.com</hostname></host><host><ip>206.82.104.202</ip><hostname>ipv4.de-cix.nyc.us.as15169.google.com</hostname></host><host><ip>202.128.15.11</ip><hostname>11.cache.google.com</hostname></host><host><ip>142.250.68.206</ip><hostname>console.actions.google.com</hostname></host><host><ip>184.23.240.34</ip><hostname>184-23-240-34.cache.google.com</hostname></host><host><ip>219.88.189.191</ip><hostname>219-88-189-191.cache.google.com</hostname></host><host><ip>135.180.176.203</ip><hostname>135-180-176-203.cache.google.com</hostname></host><host><ip>189.39.126.25</ip><hostname>25.126.39.189.cache.google.com</hostname></host><host><ip>189.124.80.98</ip><hostname>98.80.124.189.cache.google.com</hostname></host><host><ip>219.88.189.135</ip><hostname>219-88-189-135.cache.google.com</hostname></host><host><ip>186.237.52.16</ip><hostname>186-237-52-16.cache.google.com</hostname></host><host><ip>135.180.176.214</ip><hostname>135-180-176-214.cache.google.com</hostname></host><host><ip>186.237.52.28</ip><hostname>186-237-52-28.cache.google.com</hostname></host><host><ip>135.180.176.230</ip><hostname>135-180-176-230.cache.google.com</hostname></host><host><ip>92.241.132.100</ip><hostname>100-cache-blicnet.google.com</hostname></host><host><ip>142.251.45.78</ip><hostname>accelerator.google.com</hostname></host><host><ip>219.88.189.195</ip><hostname>219-88-189-195.cache.google.com</hostname></host><host><ip>135.180.176.235</ip><hostname>135-180-176-235.cache.google.com</hostname></host><host><ip>92.241.132.99</ip><hostname>99-cache-blicnet.google.com</hostname></host><host><ip>186.237.52.19</ip><hostname>186-237-52-19.cache.google.com</hostname></host><host><ip>219.88.189.151</ip><hostname>219-88-189-151.cache.google.com</hostname></host><host><ip>92.241.132.88</ip><hostname>88-cache-blicnet.google.com</hostname></host><host><ip>189.39.126.56</ip><hostname>56.126.39.189.cache.google.com</hostname></host><host><ip>135.180.176.220</ip><hostname>135-180-176-220.cache.google.com</hostname></host><host><ip>219.88.189.159</ip><hostname>219-88-189-159.cache.google.com</hostname></host><host><ip>186.237.52.0</ip><hostname>186-237-52-0.cache.google.com</hostname></host><host><ip>189.39.126.35</ip><hostname>35.126.39.189.cache.google.com</hostname></host><host><ip>142.250.105.129</ip><hostname>borgmon.evenflow-test.adz.google.com</hostname></host><host><ip>189.124.80.126</ip><hostname>126.80.124.189.cache.google.com</hostname></host><host><ip>177.129.16.121</ip><hostname>177.129.16.121.cache.google.com</hostname></host><host><ip>177.129.16.114</ip><hostname>177.129.16.114.cache.google.com</hostname></host><host><ip>184.23.240.55</ip><hostname>184-23-240-55.cache.google.com</hostname></host><host><ip>135.180.176.228</ip><hostname>135-180-176-228.cache.google.com</hostname></host><host><ip>189.124.80.125</ip><hostname>125.80.124.189.cache.google.com</hostname></host><host><ip>189.124.80.112</ip><hostname>112.80.124.189.cache.google.com</hostname></host><host><ip>92.241.132.122</ip><hostname>122-cache-blicnet.google.com</hostname></host><host><ip>189.39.126.61</ip><hostname>61.126.39.189.cache.google.com</hostname></host><host><ip>219.88.189.200</ip><hostname>219-88-189-200.cache.google.com</hostname></host><host><ip>189.124.80.84</ip><hostname>84.80.124.189.cache.google.com</hostname></host><host><ip>95.85.51.196</ip><hostname>ams2.google.com</hostname></host><host><ip>142.91.102.88</ip><hostname>1.1.1.1.hosted.by.google.com</hostname></host><host><ip>189.39.126.28</ip><hostname>28.126.39.189.cache.google.com</hostname></host><host><ip>189.39.126.47</ip><hostname>47.126.39.189.cache.google.com</hostname></host><host><ip>142.250.65.226</ip><hostname>adservice.google.com</hostname></host><host><ip>92.241.132.82</ip><hostname>82-cache-blicnet.google.com</hostname></host><host><ip>24.220.1.133</ip><hostname>133.cache.google.com</hostname></host><host><ip>186.237.52.39</ip><hostname>186-237-52-39.cache.google.com</hostname></host><host><ip>135.180.176.252</ip><hostname>135-180-176-252.cache.google.com</hostname></host><host><ip>184.23.240.50</ip><hostname>184-23-240-50.cache.google.com</hostname></host><host><ip>189.39.126.27</ip><hostname>27.126.39.189.cache.google.com</hostname></host><host><ip>92.241.132.93</ip><hostname>93-cache-blicnet.google.com</hostname></host><host><ip>92.241.132.80</ip><hostname>80-cache-blicnet.google.com</hostname></host><host><ip>216.239.33.25</ip><hostname>216-239-33-25.google.com</hostname></host><host><ip>92.241.132.127</ip><hostname>127-cache-blicnet.google.com</hostname></host><host><ip>189.124.80.100</ip><hostname>100.80.124.189.cache.google.com</hostname></host><host><ip>219.88.189.138</ip><hostname>219-88-189-138.cache.google.com</hostname></host><host><ip>135.180.176.207</ip><hostname>135-180-176-207.cache.google.com</hostname></host><host><ip>202.128.15.2</ip><hostname>2.cache.google.com</hostname></host><host><ip>186.237.52.17</ip><hostname>186-237-52-17.cache.google.com</hostname></host><host><ip>189.124.80.78</ip><hostname>78.80.124.189.cache.google.com</hostname></host><host><ip>185.1.8.100</ip><hostname>ipv4.smarthub-1.uae-ix.as15169.google.com</hostname></host><host><ip>135.180.176.224</ip><hostname>135-180-176-224.cache.google.com</hostname></host><host><ip>219.88.189.201</ip><hostname>219-88-189-201.cache.google.com</hostname></host><host><ip>186.237.52.57</ip><hostname>186-237-52-57.cache.google.com</hostname></host><host><ip>219.88.189.156</ip><hostname>219-88-189-156.cache.google.com</hostname></host><host><ip>219.88.189.194</ip><hostname>219-88-189-194.cache.google.com</hostname></host><host><ip>189.39.126.58</ip><hostname>58.126.39.189.cache.google.com</hostname></host><host><ip>219.88.189.162</ip><hostname>219-88-189-162.cache.google.com</hostname></host><host><ip>186.237.52.45</ip><hostname>186-237-52-45.cache.google.com</hostname></host><host><ip>219.88.189.180</ip><hostname>219-88-189-180.cache.google.com</hostname></host><host><ip>189.39.126.55</ip><hostname>55.126.39.189.cache.google.com</hostname></host><host><ip>186.237.52.40</ip><hostname>186-237-52-40.cache.google.com</hostname></host><host><ip>24.220.112.132</ip><hostname>132.cache.google.com</hostname></host><host><ip>186.237.52.21</ip><hostname>186-237-52-21.cache.google.com</hostname></host><host><ip>216.239.45.8</ip><hostname>216-239-45-8.google.com</hostname></host><host><ip>219.88.189.182</ip><hostname>219-88-189-182.cache.google.com</hostname></host><host><ip>219.88.189.164</ip><hostname>219-88-189-164.cache.google.com</hostname></host><host><ip>92.241.132.120</ip><hostname>120-cache-blicnet.google.com</hostname></host><host><ip>135.180.176.204</ip><hostname>135-180-176-204.cache.google.com</hostname></host><host><ip>189.39.126.30</ip><hostname>30.126.39.189.cache.google.com</hostname></host><host><ip>135.180.176.213</ip><hostname>135-180-176-213.cache.google.com</hostname></host><host><ip>185.1.208.170</ip><hostname>ipv4.de-cix.muc.de.as15169.google.com</hostname></host><host><ip>216.239.53.83</ip><hostname>216-239-53-83.google.com</hostname></host><host><ip>38.89.70.140</ip><hostname>140-70-89-38.google.com</hostname></host><host><ip>92.241.132.84</ip><hostname>84-cache-blicnet.google.com</hostname></host><host><ip>189.39.126.34</ip><hostname>34.126.39.189.cache.google.com</hostname></host><host><ip>92.241.132.70</ip><hostname>70-cache-blicnet.google.com</hostname></host><host><ip>64.233.176.101</ip><hostname>advisor.google.com</hostname></host><host><ip>186.237.52.46</ip><hostname>186-237-52-46.cache.google.com</hostname></host><host><ip>135.180.176.211</ip><hostname>135-180-176-211.cache.google.com</hostname></host><host><ip>189.124.80.117</ip><hostname>117.80.124.189.cache.google.com</hostname></host><host><ip>135.180.176.232</ip><hostname>135-180-176-232.cache.google.com</hostname></host><host><ip>184.23.240.43</ip><hostname>184-23-240-43.cache.google.com</hostname></host><host><ip>61.4.66.225</ip><hostname>cache.google.com</hostname></host><host><ip>92.241.132.118</ip><hostname>118-cache-blicnet.google.com</hostname></host><host><ip>184.23.240.54</ip><hostname>184-23-240-54.cache.google.com</hostname></host><host><ip>177.129.16.109</ip><hostname>177.129.16.109.cache.google.com</hostname></host><host><ip>92.241.132.65</ip><hostname>65-cache-blicnet.google.com</hostname></host><host><ip>135.180.176.205</ip><hostname>135-180-176-205.cache.google.com</hostname></host><host><ip>186.237.52.7</ip><hostname>186-237-52-7.cache.google.com</hostname></host><host><ip>49.13.212.183</ip><hostname>static.183.212.13.49.google.com</hostname></host><host><ip>92.241.132.86</ip><hostname>86-cache-blicnet.google.com</hostname></host><host><ip>189.39.126.24</ip><hostname>24.126.39.189.cache.google.com</hostname></host><host><ip>202.128.15.19</ip><hostname>19.cache.google.com</hostname></host><host><ip>184.23.240.42</ip><hostname>184-23-240-42.cache.google.com</hostname></host><host><ip>92.241.132.116</ip><hostname>116-cache-blicnet.google.com</hostname></host><host><ip>189.124.80.120</ip><hostname>120.80.124.189.cache.google.com</hostname></host><host><ip>219.88.189.192</ip><hostname>219-88-189-192.cache.google.com</hostname></host><host><ip>177.129.16.113</ip><hostname>177.129.16.113.cache.google.com</hostname></host><host><ip>142.250.217.14</ip><hostname>admanager.google.com</hostname></host><host><ip>92.241.132.101</ip><hostname>101-cache-blicnet.google.com</hostname></host><host><ip>64.233.176.139</ip><hostname>1.google.com</hostname></host><host><ip>92.241.132.79</ip><hostname>79-cache-blicnet.google.com</hostname></host><host><ip>92.241.132.94</ip><hostname>94-cache-blicnet.google.com</hostname></host><host><ip>184.23.240.35</ip><hostname>184-23-240-35.cache.google.com</hostname></host><host><ip>92.241.132.76</ip><hostname>76-cache-blicnet.google.com</hostname></host><host><ip>189.124.80.95</ip><hostname>95.80.124.189.cache.google.com</hostname></host><host><ip>189.39.126.4</ip><hostname>4.126.39.189.cache.google.com</hostname></host><host><ip>189.39.126.10</ip><hostname>10.126.39.189.cache.google.com</hostname></host><host><ip>135.180.176.247</ip><hostname>135-180-176-247.cache.google.com</hostname></host><host><ip>142.250.68.206</ip><hostname>about.google.com</hostname></host><host><ip>177.129.16.120</ip><hostname>177.129.16.120.cache.google.com</hostname></host><host><ip>135.180.176.200</ip><hostname>135-180-176-200.cache.google.com</hostname></host><host><ip>135.180.176.248</ip><hostname>135-180-176-248.cache.google.com</hostname></host><host><ip>189.124.80.90</ip><hostname>90.80.124.189.cache.google.com</hostname></host><host><ip>186.237.52.48</ip><hostname>186-237-52-48.cache.google.com</hostname></host><host><ip>189.39.126.3</ip><hostname>3.126.39.189.cache.google.com</hostname></host><host><ip>142.250.190.238</ip><hostname>www.ads.google.com</hostname></host><host><ip>189.39.126.16</ip><hostname>16.126.39.189.cache.google.com</hostname></host><host><ip>216.239.45.32</ip><hostname>216-239-45-32.google.com</hostname></host><host><ip>135.180.176.208</ip><hostname>135-180-176-208.cache.google.com</hostname></host><host><ip>92.241.132.97</ip><hostname>97-cache-blicnet.google.com</hostname></host><host><ip>189.39.126.29</ip><hostname>29.126.39.189.cache.google.com</hostname></host><host><ip>189.39.126.9</ip><hostname>9.126.39.189.cache.google.com</hostname></host><host><ip>216.239.32.220</ip><hostname>captive.adservice.google.com</hostname></host><host><ip>177.36.38.190</ip><hostname>177-36-38-190.cache.google.com</hostname></host><host><ip>92.241.132.64</ip><hostname>64-cache-blicnet.google.com</hostname></host><host><ip>189.39.126.8</ip><hostname>8.126.39.189.cache.google.com</hostname></host><host><ip>189.124.80.102</ip><hostname>102.80.124.189.cache.google.com</hostname></host><host><ip>186.237.52.42</ip><hostname>186-237-52-42.cache.google.com</hostname></host><host><ip>95.179.237.43</ip><hostname>basp.google.com</hostname></host><host><ip>92.241.132.106</ip><hostname>106-cache-blicnet.google.com</hostname></host><host><ip>64.233.176.138</ip><hostname>account.google.com</hostname></host><host><ip>92.241.132.81</ip><hostname>81-cache-blicnet.google.com</hostname></host><host><ip>185.1.192.25</ip><hostname>ipv4.de-cix.mad.es.as15169.google.com</hostname></host><host><ip>192.178.155.101</ip><hostname>www.adwords.google.com</hostname></host><host><ip>186.237.52.8</ip><hostname>186-237-52-8.cache.google.com</hostname></host><host><ip>219.88.189.198</ip><hostname>219-88-189-198.cache.google.com</hostname></host><host><ip>184.23.240.44</ip><hostname>184-23-240-44.cache.google.com</hostname></host><host><ip>189.39.126.60</ip><hostname>60.126.39.189.cache.google.com</hostname></host><host><ip>186.237.52.26</ip><hostname>186-237-52-26.cache.google.com</hostname></host><host><ip>189.124.80.89</ip><hostname>89.80.124.189.cache.google.com</hostname></host><host><ip>219.88.189.173</ip><hostname>219-88-189-173.cache.google.com</hostname></host><host><ip>189.124.80.75</ip><hostname>75.80.124.189.cache.google.com</hostname></host><host><ip>184.23.240.41</ip><hostname>184-23-240-41.cache.google.com</hostname></host><host><ip>135.180.176.196</ip><hostname>135-180-176-196.cache.google.com</hostname></host><host><ip>135.180.176.242</ip><hostname>135-180-176-242.cache.google.com</hostname></host><host><ip>216.239.45.10</ip><hostname>216-239-45-10.google.com</hostname></host><host><ip>184.23.240.53</ip><hostname>184-23-240-53.cache.google.com</hostname></host><host><ip>186.237.52.15</ip><hostname>186-237-52-15.cache.google.com</hostname></host><host><ip>24.220.112.165</ip><hostname>165.cache.google.com</hostname></host><host><ip>216.239.45.6</ip><hostname>216-239-45-6.google.com</hostname></host><host><ip>24.220.1.134</ip><hostname>134.cache.google.com</hostname></host><host><ip>167.179.119.143</ip><hostname>167.179.119.143.google.com</hostname></host><host><ip>189.39.126.39</ip><hostname>39.126.39.189.cache.google.com</hostname></host><host><ip>219.88.189.144</ip><hostname>219-88-189-144.cache.google.com</hostname></host><host><ip>142.250.188.14</ip><hostname>adx.google.com</hostname></host><host><ip>184.23.240.52</ip><hostname>184-23-240-52.cache.google.com</hostname></host><host><ip>67.219.192.63</ip><hostname>broadcast.google.com</hostname></host><host><ip>142.250.68.206</ip><hostname>actions.google.com</hostname></host><host><ip>103.208.27.189</ip><hostname>accounts.google.com</hostname></host><host><ip>216.239.45.34</ip><hostname>216-239-45-34.google.com</hostname></host><host><ip>185.1.119.28</ip><hostname>ipv4.de-cix.bcn.es.as15169.google.com</hostname></host><host><ip>177.129.16.111</ip><hostname>177.129.16.111.cache.google.com</hostname></host><host><ip>219.88.189.165</ip><hostname>219-88-189-165.cache.google.com</hostname></host><host><ip>216.239.53.81</ip><hostname>216-239-53-81.google.com</hostname></host><host><ip>177.129.16.104</ip><hostname>177.129.16.104.cache.google.com</hostname></host></theHarvester>