[{"session_id": "8.8.8.8", "provider": "okta", "total_ms": 400, "steps": [{"ms": 0, "action": "Alert ingested", "status": "OK", "detail": "Stealer log match confirmed for session 8.8.8.8"}, {"ms": 50, "action": "Session validated", "status": "OK", "detail": "Active session confirmed via OKTA API"}, {"ms": 200, "action": "Session revoked", "status": "OK", "detail": "revoke_user_sessions API call successful \u2014 all tokens invalidated"}, {"ms": 210, "action": "IP blocklisted", "status": "OK", "detail": "Attacker IP added to firewall blocklist via pfSense API"}, {"ms": 380, "action": "SOC alert sent", "status": "OK", "detail": "Incident logged + Telegram alert dispatched"}, {"ms": 400, "action": "RESOLVED", "status": "OK", "detail": "Full kill chain executed \u2014 zero human intervention required"}], "timestamp": "2026-04-17T03:05:37.066903"}]